m2m_mcp_server_ssh_client/__init__.py
m2m_mcp_server_ssh_client/__main__.py
m2m_mcp_server_ssh_client/proxy_server.py
m2m_mcp_server_ssh_client/ssh_client.py
iflow_mcp_m2m_mcp_server_ssh_client-0.1.3.dist-info/METADATA
iflow_mcp_m2m_mcp_server_ssh_client-0.1.3.dist-info/WHEEL
iflow_mcp_m2m_mcp_server_ssh_client-0.1.3.dist-info/entry_points.txt
iflow_mcp_m2m_mcp_server_ssh_client-0.1.3.dist-info/licenses/LICENSE
iflow_mcp_m2m_mcp_server_ssh_client-0.1.3.dist-info/RECORD
