Metadata-Version: 2.4
Name: iflow-mcp_m2m-mcp-server-ssh-client
Version: 0.1.3
Summary: A stdio-based MCP server installed locally to connect to a (remote) MCP server group through a secure SSH channel
Project-URL: Homepage, https://www.machinetomachine.ai/
Project-URL: Repository, https://github.com/Machine-To-Machine/m2m-mcp-server-ssh-client.git
Project-URL: Issues, https://github.com/Machine-To-Machine/m2m-mcp-server-ssh-client/issues
Project-URL: Documentation, https://github.com/Machine-To-Machine/m2m-mcp-server-ssh-client/blob/main/README.md
Project-URL: Changelog, https://github.com/Machine-To-Machine/m2m-mcp-server-ssh-client/blob/main/CHANGELOG.md
Project-URL: Source Code, https://github.com/Machine-To-Machine/m2m-mcp-server-ssh-client
Project-URL: Security, https://github.com/Machine-To-Machine/m2m-mcp-server-ssh-client/blob/main/SECURITY.md
Author: Machine To Machine
Maintainer-email: Will Pak <will@machinetomachine.ai>, "Harold Bott Jr." <harold@machinetomachine.ai>
License: MIT
License-File: LICENSE
Keywords: automation,client,decentralized,llm,m2m,mcp,remote,ssh
Classifier: Development Status :: 4 - Beta
Classifier: Intended Audience :: Developers
Classifier: License :: OSI Approved :: MIT License
Classifier: Programming Language :: Python :: 3
Classifier: Programming Language :: Python :: 3.10
Classifier: Programming Language :: Python :: 3.11
Classifier: Programming Language :: Python :: 3.12
Classifier: Programming Language :: Python :: 3.13
Requires-Python: >=3.10
Requires-Dist: anyio>=4.5
Requires-Dist: asyncssh>=2.20.0
Requires-Dist: httpx>=0.24.0
Requires-Dist: mcp>=1.10.1
Requires-Dist: pydantic>=2.0.0
